setup.py
mem_test_probability/Binomialdistribution.py
mem_test_probability/Gaussiandistribution.py
mem_test_probability/Generaldistribution.py
mem_test_probability/__init__.py
mem_test_probability.egg-info/PKG-INFO
mem_test_probability.egg-info/SOURCES.txt
mem_test_probability.egg-info/dependency_links.txt
mem_test_probability.egg-info/not-zip-safe
mem_test_probability.egg-info/top_level.txt